README.rst
setup.py
SimpleMathCalc/Average.py
SimpleMathCalc/Hex_conversion_decimal_binary.py
SimpleMathCalc/Hex_conversion_decimal_hexadecimal.py
SimpleMathCalc/Inverse_trigonometric_function.py
SimpleMathCalc/Median.py
SimpleMathCalc/Mode_number.py
SimpleMathCalc/Trigonometric_function.py
SimpleMathCalc/__init__.py
SimpleMathCalc/arithmometer.py
SimpleMathCalc/square.py
SimpleMathCalc.egg-info/PKG-INFO
SimpleMathCalc.egg-info/SOURCES.txt
SimpleMathCalc.egg-info/dependency_links.txt
SimpleMathCalc.egg-info/top_level.txt