Metadata-Version: 1.0
Name: SimpleMathCalc
Version: 0.1
Summary: This is calculator that can calculate arithmometer, average number, median number, mode number, hex conversion, square and so on. Don't except you will be cool using this calc, it is like a poetaster! But anyway I learned how to share this project on Github and tried to publish it to PyPI
Home-page: https://github.com/BingliangLI/SimpleMathCalc
Author: LZU_Group_5
Author-email: blli18@lzu.edu.cn
License: GNU General Public License v3.0
Keywords: calculator
Platform: UNKNOWN
